Workbook
Name G-FREIGHT: RFQ_QUOTES!$B$2
Name G-DUTY: RFQ_QUOTES!$D$2
Name G-QC: RFQ_QUOTES!$F$2
Name G-FX: RFQ_QUOTES!$H$2
Name G-PLATFORM: RFQ_QUOTES!$J$2
Name G-RETURNS: RFQ_QUOTES!$L$2

Sheet DASHBOARD
A1: LIONNA™ — Collection & Supplier Management System · SS27
A2: She Moves. The World Adjusts. · Phase 1 · Spring/Summer 2027 · Generated: 24 Jun 2026
A4: TOTAL SKUs | C4: TOTAL UNITS | E4: SUPPLIERS | G4: APPROVED | I4: QUOTES RCVD
A5: =COUNTA(COLLECTION[SKU#])-1 | C5: =SUM(COLLECTION[Total Units]) | E5: =COUNTA(SUPPLIERS[Supplier Name])-1 | G5: =COUNTIF(SUPPLIERS[Status],"Approved") | I5: =COUNTA(RFQ_QUOTES[Quote ID])-1
A6: # SKUs Phase 1 | C6: pcs across all SKUs | E6: identified OEM partners | G6: approved for RFQ | I6: of all suppliers
A8: HOW TO USE THIS WORKBOOK
A9: SUPPLIERS sheet | B9: Add all OEM suppliers with contact, URL, MOQ, lead time. Update Status column as relationship progresses.
A10: SCORING sheet | B10: Enter scores 0–10 for each supplier variable. System auto-ranks and flags Approve/Negotiate/Reject.
A11: RFQ_QUOTES sheet | B11: Log every quote received from suppliers. Landed cost and margin calculated automatically.
A12: FOB_D2D sheet | B12: Adjust global assumptions (freight %, duty %, FX rate) — all calculations update across the workbook.
A13: COLLECTION sheet | B13: Full SKU list by moment. Enter FOB when quotes arrive to see real-time margin per piece.
A14: FABRICS sheet | B14: Fabric library with GSM, composition, and Golden Rule compliance tracking.
A15: PRINT AREA | B15: Each sheet has a defined print area. Use File → Print to generate PDF for OEM briefs.

Sheet SUPPLIERS
A1: LIONNA™ — Supplier Directory & CRM
A2: Supplier Name | B2: Priority | C2: Contact Name | D2: Email | E2: WeChat/WhatsApp | F2: City | G2: Country | H2: Alibaba URL | I2: Speciality | J2: Fabric Capability | K2: MOQ/Color | L2: MOQ/Size Run | M2: Lead Time (days) | N2: Certifications | O2: Design Cap. | P2: Customization | Q2: Status | R2: Notes | S2: Overall Score
A3: EnovStars | B3: 1 | C3: Sales Team | F3: Guangdong | G3: China | H3: https://www.alibaba.com/product-detail/EnovStars-OEM-Activewear-Set-78-Nylon_1601730014349.html | I3: Leggings·Bra·Tank·Skirt·Jacket | J3: 78% Nylon 22% Spandex | K3: 50 | L3: 50 | M3: 45 | O3: Moderate | P3: Full | Q3: Approved | R3: Top priority. Naked Feel fabric = LIONNA spec. | S3: =IFERROR(VLOOKUP(A3,SCORING!A:B,2,0),"")
A4: Tennis Jumpsuit #24 | B4: 2 | F4: China | G4: China | H4: https://www.alibaba.com/product-detail/High-Quality-Women-s-Sports-Tennis_1601724763174.html | I4: Jumpsuit·Coverage Skirt | J4: Nylon/Spandex | K4: 50 | L4: 50 | M4: 40 | O4: Basic | P4: Embroidery | Q4: Approved | R4: Only supplier with jumpsuit + skirt system. | S4: =IFERROR(VLOOKUP(A4,SCORING!A:B,2,0),"")
A5: AlOe / FITVOLT | B5: 3 | F5: China | G5: China | H5: https://www.alibaba.com/product-detail/AlOe-Women-s-Spring-Quick-Dry_1601819685647.html | I5: Wide-Leg·Straight-Leg Pants | J5: 4-way stretch tech fabric | K5: 50 | L5: 50 | M5: 40 | O5: Basic | P5: Label only | Q5: Approved | R5: Two pant silhouettes. Complete The Work drop. | S5: =IFERROR(VLOOKUP(A5,SCORING!A:B,2,0),"")
A6: Anti-Exposure Shorts #15 | B6: 4 | F6: China | G6: China | H6: https://www.alibaba.com/product-detail/Running-Workout-High-Waist-Short-Sets_1601407705414.html | I6: Biker Short·Relaxed Short | J6: Nylon/Spandex (confirm) | K6: 50 | L6: 50 | M6: 45 | O6: None | P6: Label only | Q6: Contacted | R6: Anti-exposure language = LIONNA spec. | S6: =IFERROR(VLOOKUP(A6,SCORING!A:B,2,0),"")
A7: Crossback Bra #5 | B7: 5 | F7: China | G7: China | H7: https://www.alibaba.com/product-detail/OEM-Custom-Crossover-Workout-Gym-Back_1601789816721.html | I7: Sports Bra·Crop Top | J7: Nylon/Spandex (confirm) | K7: 100 | L7: 100 | M7: 50 | O7: Basic | P7: Embroidery | Q7: Pending | R7: Elegant crossback with side pockets. | S7: =IFERROR(VLOOKUP(A7,SCORING!A:B,2,0),"")
A8: QUMOR #30 | B8: 6 | F8: China | G8: China | H8: https://www.alibaba.com/product-detail/QUMOR-Women-s-Summer-Yoga-Set_1601761982075.html | I8: Tennis Skort·Sport Skirt | J8: Breathable nylon | K8: 50 | L8: 50 | M8: 45 | O8: Basic | P8: Label only | Q8: Pending | R8: Tennis skort with coverage undershort. | S8: =IFERROR(VLOOKUP(A8,SCORING!A:B,2,0),"")
S9: =IFERROR(VLOOKUP(A9,SCORING!A:B,2,0),"")
S10: =IFERROR(VLOOKUP(A10,SCORING!A:B,2,0),"")
S11: =IFERROR(VLOOKUP(A11,SCORING!A:B,2,0),"")
S12: =IFERROR(VLOOKUP(A12,SCORING!A:B,2,0),"")
S13: =IFERROR(VLOOKUP(A13,SCORING!A:B,2,0),"")
S14: =IFERROR(VLOOKUP(A14,SCORING!A:B,2,0),"")
S15: =IFERROR(VLOOKUP(A15,SCORING!A:B,2,0),"")
S16: =IFERROR(VLOOKUP(A16,SCORING!A:B,2,0),"")
S17: =IFERROR(VLOOKUP(A17,SCORING!A:B,2,0),"")
S18: =IFERROR(VLOOKUP(A18,SCORING!A:B,2,0),"")
S19: =IFERROR(VLOOKUP(A19,SCORING!A:B,2,0),"")
S20: =IFERROR(VLOOKUP(A20,SCORING!A:B,2,0),"")
... S24: =IFERROR(VLOOKUP(A24,SCORING!A:B,2,0),"")

Sheet SCORING
A1: LIONNA™ — Supplier Scoring Model · Multi-Variable Mathematical Evaluation
A2: VARIABLE WEIGHTS (must sum to 100%) | C2: 20 | D2: 18 | E2: 16 | F2: 10 | G2: 10 | H2: 8 | I2: 8 | J2: 5 | K2: 5
A3: WEIGHT TOTAL (must = 100): | C3: =SUM(C2:K2)
A5: Supplier Name | B5: Total Score | C5: FOB Price (w=20%) | D5: D2D Margin (w=18%) | E5: Fabric Quality (w=16%) | F5: Design Cap (w=10%) | G5: Lead Time (w=10%) | H5: Freight/Access (w=8%) | I5: Customization (w=8%) | J5: MOQ/Color (w=5%) | K5: MOQ/Size Run (w=5%) | L5: DECISION
A6: EnovStars | B6: =ROUND(SUMPRODUCT(C6:K6,C$2:K$2)/SUM(C$2:K$2),0) | C6: 8 | D6: 8 | E6: 9 | F6: 7 | G6: 8 | H6: 7 | I6: 9 | J6: 9 | K6: 9 | L6: =IF(B6>=75,"✅ APPROVE",IF(B6>=55,"⚠️ NEGOTIATE","❌ REJECT"))
A7: Tennis Jumpsuit #24 | B7: =ROUND(SUMPRODUCT(C7:K7,C$2:K$2)/SUM(C$2:K$2),0) | C7: 7 | D7: 7 | E7: 8 | F7: 5 | G7: 9 | H7: 7 | I7: 6 | J7: 9 | K7: 8 | L7: =IF(B7>=75,"✅ APPROVE",IF(B7>=55,"⚠️ NEGOTIATE","❌ REJECT"))
A8: AlOe / FITVOLT | B8: =ROUND(SUMPRODUCT(C8:K8,C$2:K$2)/SUM(C$2:K$2),0) | C8: 7 | D8: 7 | E8: 7 | F8: 5 | G8: 9 | H8: 7 | I8: 5 | J8: 9 | K8: 8 | L8: =IF(B8>=75,"✅ APPROVE",IF(B8>=55,"⚠️ NEGOTIATE","❌ REJECT"))
A9: Anti-Exposure Shorts #15 | B9: =ROUND(SUMPRODUCT(C9:K9,C$2:K$2)/SUM(C$2:K$2),0) | C9: 8 | D9: 8 | E9: 6 | F9: 3 | G9: 7 | H9: 6 | I9: 4 | J9: 9 | K9: 7 | L9: =IF(B9>=75,"✅ APPROVE",IF(B9>=55,"⚠️ NEGOTIATE","❌ REJECT"))
A10: Crossback Bra #5 | B10: =ROUND(SUMPRODUCT(C10:K10,C$2:K$2)/SUM(C$2:K$2),0) | C10: 6 | D10: 6 | E10: 7 | F10: 5 | G10: 6 | H10: 6 | I10: 6 | J10: 6 | K10: 6 | L10: =IF(B10>=75,"✅ APPROVE",IF(B10>=55,"⚠️ NEGOTIATE","❌ REJECT"))
A11: QUMOR #30 | B11: =ROUND(SUMPRODUCT(C11:K11,C$2:K$2)/SUM(C$2:K$2),0) | C11: 7 | D11: 7 | E11: 7 | F11: 4 | G11: 7 | H11: 6 | I11: 5 | J11: 9 | K11: 7 | L11: =IF(B11>=75,"✅ APPROVE",IF(B11>=55,"⚠️ NEGOTIATE","❌ REJECT"))
B12: =IF(A12<>"",ROUND(SUMPRODUCT(C12:K12,C$2:K$2)/SUM(C$2:K$2),0),"") | L12: =IF(A12<>"",IF(B12>=75,"✅ APPROVE",IF(B12>=55,"⚠️ NEGOTIATE","❌ REJECT")),"")
B13: =IF(A13<>"",ROUND(SUMPRODUCT(C13:K13,C$2:K$2)/SUM(C$2:K$2),0),"") | L13: =IF(A13<>"",IF(B13>=75,"✅ APPROVE",IF(B13>=55,"⚠️ NEGOTIATE","❌ REJECT")),"")
B14: =IF(A14<>"",ROUND(SUMPRODUCT(C14:K14,C$2:K$2)/SUM(C$2:K$2),0),"") | L14: =IF(A14<>"",IF(B14>=75,"✅ APPROVE",IF(B14>=55,"⚠️ NEGOTIATE","❌ REJECT")),"")
B15: =IF(A15<>"",ROUND(SUMPRODUCT(C15:K15,C$2:K$2)/SUM(C$2:K$2),0),"") | L15: =IF(A15<>"",IF(B15>=75,"✅ APPROVE",IF(B15>=55,"⚠️ NEGOTIATE","❌ REJECT")),"")
B16: =IF(A16<>"",ROUND(SUMPRODUCT(C16:K16,C$2:K$2)/SUM(C$2:K$2),0),"") | L16: =IF(A16<>"",IF(B16>=75,"✅ APPROVE",IF(B16>=55,"⚠️ NEGOTIATE","❌ REJECT")),"")
B17: =IF(A17<>"",ROUND(SUMPRODUCT(C17:K17,C$2:K$2)/SUM(C$2:K$2),0),"") | L17: =IF(A17<>"",IF(B17>=75,"✅ APPROVE",IF(B17>=55,"⚠️ NEGOTIATE","❌ REJECT")),"")
B18: =IF(A18<>"",ROUND(SUMPRODUCT(C18:K18,C$2:K$2)/SUM(C$2:K$2),0),"") | L18: =IF(A18<>"",IF(B18>=75,"✅ APPROVE",IF(B18>=55,"⚠️ NEGOTIATE","❌ REJECT")),"")
B19: =IF(A19<>"",ROUND(SUMPRODUCT(C19:K19,C$2:K$2)/SUM(C$2:K$2),0),"") | L19: =IF(A19<>"",IF(B19>=75,"✅ APPROVE",IF(B19>=55,"⚠️ NEGOTIATE","❌ REJECT")),"")
A22: SCORING GUIDE
A23: FOB Price | B23: 10=<$10/unit · 8=$10–14 · 6=$14–18 · 4=$18–22 · 2=>$22 | J23: Lowest = Best
A24: D2D Margin | B24: 10=>55% gross · 8=45–55% · 6=35–45% · 4=25–35% · 2=<25% | J24: Calculated from FOB and retail
A25: Fabric Quality | B25: 10=78% Nylon/Spandex confirmed · 8=Nylon blend · 5=Tech poly · 2=Cotton/basic | J25: LIONNA requires nylon/spandex
A26: Design Capability | B26: 10=Full design from brief · 7=Moderate · 4=Minor mods · 1=None | J26: Important for silhouette accuracy
A27: Lead Time | B27: 10=<35 days · 8=35–50 · 6=50–65 · 4=65–80 · 2=>80 | J27: Days from order to ex-factory
A28: Freight / Access | B28: 10=FOB major port · 7=Std logistics · 4=Remote location | J28: Export ease and port access
A29: Customization | B29: 10=Full (label+emb+hangtag+jacquard) · 6=Partial · 2=None | J29: LIONNA needs full package
A30: MOQ/Color | B30: 10=≤50 pcs · 7=51–100 · 4=101–200 · 1=>200 | J30: LIONNA target: 50 pcs/color
A31: MOQ/Size Run | B31: 10=Accepts 5 sizes in 1 MOQ · 6=Some flexibility · 2=Strict | J31: Must accept PP,P,M,G,GG

Sheet RFQ_QUOTES
A1: LIONNA™ — RFQ-SS27-001 · Quote Log & Landed Cost Analysis
A2: Freight % | B2: 18 | C2: Import Duty % | D2: 20 | E2: QC & Misc % | F2: 8 | G2: USD/BRL Rate | H2: 5.2 | I2: Platform Fee % | J2: 12 | K2: Return Rate % | L2: 8
A3: Quote ID | B3: Supplier | C3: SKU # | D3: Style Name | E3: FOB Price (USD) | F3: Freight (USD) | G3: Duty (USD) | H3: QC Cost (USD) | I3: Landed (USD) | J3: FX Rate | K3: Landed (R$) | L3: Retail Min (R$) | M3: Retail Max (R$) | N3: Gross Margin % | O3: Net Margin % | P3: MOQ/Color | Q3: Lead Time (days) | R3: Sample Cost | S3: Status | T3: Notes
A4: =IF(B4<>"","Q-"&TEXT(ROW()-3,"000"),"") | F4: =IF(E4<>"",E4*B2/100,"") | G4: =IF(E4<>"",E4*D2/100,"") | H4: =IF(E4<>"",E4*F2/100,"") | I4: =IF(E4<>"",E4+F4+G4+H4,"") | J4: =IF(E4<>"",H2,"") | K4: =IF(I4<>"",I4*J4,"") | N4: =IF(AND(K4<>"",L4<>""),(L4-K4)/L4,"") | O4: =IF(N4<>"",N4-J2/100-L2/100,"")
A5: =IF(B5<>"","Q-"&TEXT(ROW()-3,"000"),"") | F5: =IF(E5<>"",E5*B2/100,"") | G5: =IF(E5<>"",E5*D2/100,"") | H5: =IF(E5<>"",E5*F2/100,"") | I5: =IF(E5<>"",E5+F5+G5+H5,"") | J5: =IF(E5<>"",H2,"") | K5: =IF(I5<>"",I5*J5,"") | N5: =IF(AND(K5<>"",L5<>""),(L5-K5)/L5,"") | O5: =IF(N5<>"",N5-J2/100-L2/100,"")
A6: =IF(B6<>"","Q-"&TEXT(ROW()-3,"000"),"") | F6: =IF(E6<>"",E6*B2/100,"") | G6: =IF(E6<>"",E6*D2/100,"") | H6: =IF(E6<>"",E6*F2/100,"") | I6: =IF(E6<>"",E6+F6+G6+H6,"") | J6: =IF(E6<>"",H2,"") | K6: =IF(I6<>"",I6*J6,"") | N6: =IF(AND(K6<>"",L6<>""),(L6-K6)/L6,"") | O6: =IF(N6<>"",N6-J2/100-L2/100,"")
A7: =IF(B7<>"","Q-"&TEXT(ROW()-3,"000"),"") | F7: =IF(E7<>"",E7*B2/100,"") | G7: =IF(E7<>"",E7*D2/100,"") | H7: =IF(E7<>"",E7*F2/100,"") | I7: =IF(E7<>"",E7+F7+G7+H7,"") | J7: =IF(E7<>"",H2,"") | K7: =IF(I7<>"",I7*J7,"") | N7: =IF(AND(K7<>"",L7<>""),(L7-K7)/L7,"") | O7: =IF(N7<>"",N7-J2/100-L2/100,"")
A8: =IF(B8<>"","Q-"&TEXT(ROW()-3,"000"),"") | F8: =IF(E8<>"",E8*B2/100,"") | G8: =IF(E8<>"",E8*D2/100,"") | H8: =IF(E8<>"",E8*F2/100,"") | I8: =IF(E8<>"",E8+F8+G8+H8,"") | J8: =IF(E8<>"",H2,"") | K8: =IF(I8<>"",I8*J8,"") | N8: =IF(AND(K8<>"",L8<>""),(L8-K8)/L8,"") | O8: =IF(N8<>"",N8-J2/100-L2/100,"")
A9: =IF(B9<>"","Q-"&TEXT(ROW()-3,"000"),"") | F9: =IF(E9<>"",E9*B2/100,"") | G9: =IF(E9<>"",E9*D2/100,"") | H9: =IF(E9<>"",E9*F2/100,"") | I9: =IF(E9<>"",E9+F9+G9+H9,"") | J9: =IF(E9<>"",H2,"") | K9: =IF(I9<>"",I9*J9,"") | N9: =IF(AND(K9<>"",L9<>""),(L9-K9)/L9,"") | O9: =IF(N9<>"",N9-J2/100-L2/100,"")
A10: =IF(B10<>"","Q-"&TEXT(ROW()-3,"000"),"") | F10: =IF(E10<>"",E10*B2/100,"") | G10: =IF(E10<>"",E10*D2/100,"") | H10: =IF(E10<>"",E10*F2/100,"") | I10: =IF(E10<>"",E10+F10+G10+H10,"") | J10: =IF(E10<>"",H2,"") | K10: =IF(I10<>"",I10*J10,"") | N10: =IF(AND(K10<>"",L10<>""),(L10-K10)/L10,"") | O10: =IF(N10<>"",N10-J2/100-L2/100,"")
A11: =IF(B11<>"","Q-"&TEXT(ROW()-3,"000"),"") | F11: =IF(E11<>"",E11*B2/100,"") | G11: =IF(E11<>"",E11*D2/100,"") | H11: =IF(E11<>"",E11*F2/100,"") | I11: =IF(E11<>"",E11+F11+G11+H11,"") | J11: =IF(E11<>"",H2,"") | K11: =IF(I11<>"",I11*J11,"") | N11: =IF(AND(K11<>"",L11<>""),(L11-K11)/L11,"") | O11: =IF(N11<>"",N11-J2/100-L2/100,"")
A12: =IF(B12<>"","Q-"&TEXT(ROW()-3,"000"),"") | F12: =IF(E12<>"",E12*B2/100,"") | G12: =IF(E12<>"",E12*D2/100,"") | H12: =IF(E12<>"",E12*F2/100,"") | I12: =IF(E12<>"",E12+F12+G12+H12,"") | J12: =IF(E12<>"",H2,"") | K12: =IF(I12<>"",I12*J12,"") | N12: =IF(AND(K12<>"",L12<>""),(L12-K12)/L12,"") | O12: =IF(N12<>"",N12-J2/100-L2/100,"")
A13: =IF(B13<>"","Q-"&TEXT(ROW()-3,"000"),"") | F13: =IF(E13<>"",E13*B2/100,"") | G13: =IF(E13<>"",E13*D2/100,"") | H13: =IF(E13<>"",E13*F2/100,"") | I13: =IF(E13<>"",E13+F13+G13+H13,"") | J13: =IF(E13<>"",H2,"") | K13: =IF(I13<>"",I13*J13,"") | N13: =IF(AND(K13<>"",L13<>""),(L13-K13)/L13,"") | O13: =IF(N13<>"",N13-J2/100-L2/100,"")
A14: =IF(B14<>"","Q-"&TEXT(ROW()-3,"000"),"") | F14: =IF(E14<>"",E14*B2/100,"") | G14: =IF(E14<>"",E14*D2/100,"") | H14: =IF(E14<>"",E14*F2/100,"") | I14: =IF(E14<>"",E14+F14+G14+H14,"") | J14: =IF(E14<>"",H2,"") | K14: =IF(I14<>"",I14*J14,"") | N14: =IF(AND(K14<>"",L14<>""),(L14-K14)/L14,"") | O14: =IF(N14<>"",N14-J2/100-L2/100,"")
A15: =IF(B15<>"","Q-"&TEXT(ROW()-3,"000"),"") | F15: =IF(E15<>"",E15*B2/100,"") | G15: =IF(E15<>"",E15*D2/100,"") | H15: =IF(E15<>"",E15*F2/100,"") | I15: =IF(E15<>"",E15+F15+G15+H15,"") | J15: =IF(E15<>"",H2,"") | K15: =IF(I15<>"",I15*J15,"") | N15: =IF(AND(K15<>"",L15<>""),(L15-K15)/L15,"") | O15: =IF(N15<>"",N15-J2/100-L2/100,"")
A16: =IF(B16<>"","Q-"&TEXT(ROW()-3,"000"),"") | F16: =IF(E16<>"",E16*B2/100,"") | G16: =IF(E16<>"",E16*D2/100,"") | H16: =IF(E16<>"",E16*F2/100,"") | I16: =IF(E16<>"",E16+F16+G16+H16,"") | J16: =IF(E16<>"",H2,"") | K16: =IF(I16<>"",I16*J16,"") | N16: =IF(AND(K16<>"",L16<>""),(L16-K16)/L16,"") | O16: =IF(N16<>"",N16-J2/100-L2/100,"")
A17: =IF(B17<>"","Q-"&TEXT(ROW()-3,"000"),"") | F17: =IF(E17<>"",E17*B2/100,"") | G17: =IF(E17<>"",E17*D2/100,"") | H17: =IF(E17<>"",E17*F2/100,"") | I17: =IF(E17<>"",E17+F17+G17+H17,"") | J17: =IF(E17<>"",H2,"") | K17: =IF(I17<>"",I17*J17,"") | N17: =IF(AND(K17<>"",L17<>""),(L17-K17)/L17,"") | O17: =IF(N17<>"",N17-J2/100-L2/100,"")
A18: =IF(B18<>"","Q-"&TEXT(ROW()-3,"000"),"") | F18: =IF(E18<>"",E18*B2/100,"") | G18: =IF(E18<>"",E18*D2/100,"") | H18: =IF(E18<>"",E18*F2/100,"") | I18: =IF(E18<>"",E18+F18+G18+H18,"") | J18: =IF(E18<>"",H2,"") | K18: =IF(I18<>"",I18*J18,"") | N18: =IF(AND(K18<>"",L18<>""),(L18-K18)/L18,"") | O18: =IF(N18<>"",N18-J2/100-L2/100,"")
A19: =IF(B19<>"","Q-"&TEXT(ROW()-3,"000"),"") | F19: =IF(E19<>"",E19*B2/100,"") | G19: =IF(E19<>"",E19*D2/100,"") | H19: =IF(E19<>"",E19*F2/100,"") | I19: =IF(E19<>"",E19+F19+G19+H19,"") | J19: =IF(E19<>"",H2,"") | K19: =IF(I19<>"",I19*J19,"") | N19: =IF(AND(K19<>"",L19<>""),(L19-K19)/L19,"") | O19: =IF(N19<>"",N19-J2/100-L2/100,"")
A20: =IF(B20<>"","Q-"&TEXT(ROW()-3,"000"),"") | F20: =IF(E20<>"",E20*B2/100,"") | G20: =IF(E20<>"",E20*D2/100,"") | H20: =IF(E20<>"",E20*F2/100,"") | I20: =IF(E20<>"",E20+F20+G20+H20,"") | J20: =IF(E20<>"",H2,"") | K20: =IF(I20<>"",I20*J20,"") | N20: =IF(AND(K20<>"",L20<>""),(L20-K20)/L20,"") | O20: =IF(N20<>"",N20-J2/100-L2/100,"")
A21: =IF(B21<>"","Q-"&TEXT(ROW()-3,"000"),"") | F21: =IF(E21<>"",E21*B2/100,"") | G21: =IF(E21<>"",E21*D2/100,"") | H21: =IF(E21<>"",E21*F2/100,"") | I21: =IF(E21<>"",E21+F21+G21+H21,"") | J21: =IF(E21<>"",H2,"") | K21: =IF(I21<>"",I21*J21,"") | N21: =IF(AND(K21<>"",L21<>""),(L21-K21)/L21,"") | O21: =IF(N21<>"",N21-J2/100-L2/100,"")
A22: =IF(B22<>"","Q-"&TEXT(ROW()-3,"000"),"") | F22: =IF(E22<>"",E22*B2/100,"") | G22: =IF(E22<>"",E22*D2/100,"") | H22: =IF(E22<>"",E22*F2/100,"") | I22: =IF(E22<>"",E22+F22+G22+H22,"") | J22: =IF(E22<>"",H2,"") | K22: =IF(I22<>"",I22*J22,"") | N22: =IF(AND(K22<>"",L22<>""),(L22-K22)/L22,"") | O22: =IF(N22<>"",N22-J2/100-L2/100,"")
A23: =IF(B23<>"","Q-"&TEXT(ROW()-3,"000"),"") | F23: =IF(E23<>"",E23*B2/100,"") | G23: =IF(E23<>"",E23*D2/100,"") | H23: =IF(E23<>"",E23*F2/100,"") | I23: =IF(E23<>"",E23+F23+G23+H23,"") | J23: =IF(E23<>"",H2,"") | K23: =IF(I23<>"",I23*J23,"") | N23: =IF(AND(K23<>"",L23<>""),(L23-K23)/L23,"") | O23: =IF(N23<>"",N23-J2/100-L2/100,"")
A24: =IF(B24<>"","Q-"&TEXT(ROW()-3,"000"),"") | F24: =IF(E24<>"",E24*B2/100,"") | G24: =IF(E24<>"",E24*D2/100,"") | H24: =IF(E24<>"",E24*F2/100,"") | I24: =IF(E24<>"",E24+F24+G24+H24,"") | J24: =IF(E24<>"",H2,"") | K24: =IF(I24<>"",I24*J24,"") | N24: =IF(AND(K24<>"",L24<>""),(L24-K24)/L24,"") | O24: =IF(N24<>"",N24-J2/100-L2/100,"")
A25: =IF(B25<>"","Q-"&TEXT(ROW()-3,"000"),"") | F25: =IF(E25<>"",E25*B2/100,"") | G25: =IF(E25<>"",E25*D2/100,"") | H25: =IF(E25<>"",E25*F2/100,"") | I25: =IF(E25<>"",E25+F25+G25+H25,"") | J25: =IF(E25<>"",H2,"") | K25: =IF(I25<>"",I25*J25,"") | N25: =IF(AND(K25<>"",L25<>""),(L25-K25)/L25,"") | O25: =IF(N25<>"",N25-J2/100-L2/100,"")
A26: =IF(B26<>"","Q-"&TEXT(ROW()-3,"000"),"") | F26: =IF(E26<>"",E26*B2/100,"") | G26: =IF(E26<>"",E26*D2/100,"") | H26: =IF(E26<>"",E26*F2/100,"") | I26: =IF(E26<>"",E26+F26+G26+H26,"") | J26: =IF(E26<>"",H2,"") | K26: =IF(I26<>"",I26*J26,"") | N26: =IF(AND(K26<>"",L26<>""),(L26-K26)/L26,"") | O26: =IF(N26<>"",N26-J2/100-L2/100,"")
A27: =IF(B27<>"","Q-"&TEXT(ROW()-3,"000"),"") | F27: =IF(E27<>"",E27*B2/100,"") | G27: =IF(E27<>"",E27*D2/100,"") | H27: =IF(E27<>"",E27*F2/100,"") | I27: =IF(E27<>"",E27+F27+G27+H27,"") | J27: =IF(E27<>"",H2,"") | K27: =IF(I27<>"",I27*J27,"") | N27: =IF(AND(K27<>"",L27<>""),(L27-K27)/L27,"") | O27: =IF(N27<>"",N27-J2/100-L2/100,"")
A28: =IF(B28<>"","Q-"&TEXT(ROW()-3,"000"),"") | F28: =IF(E28<>"",E28*B2/100,"") | G28: =IF(E28<>"",E28*D2/100,"") | H28: =IF(E28<>"",E28*F2/100,"") | I28: =IF(E28<>"",E28+F28+G28+H28,"") | J28: =IF(E28<>"",H2,"") | K28: =IF(I28<>"",I28*J28,"") | N28: =IF(AND(K28<>"",L28<>""),(L28-K28)/L28,"") | O28: =IF(N28<>"",N28-J2/100-L2/100,"")
A29: =IF(B29<>"","Q-"&TEXT(ROW()-3,"000"),"") | F29: =IF(E29<>"",E29*B2/100,"") | G29: =IF(E29<>"",E29*D2/100,"") | H29: =IF(E29<>"",E29*F2/100,"") | I29: =IF(E29<>"",E29+F29+G29+H29,"") | J29: =IF(E29<>"",H2,"") | K29: =IF(I29<>"",I29*J29,"") | N29: =IF(AND(K29<>"",L29<>""),(L29-K29)/L29,"") | O29: =IF(N29<>"",N29-J2/100-L2/100,"")
A30: =IF(B30<>"","Q-"&TEXT(ROW()-3,"000"),"") | F30: =IF(E30<>"",E30*B2/100,"") | G30: =IF(E30<>"",E30*D2/100,"") | H30: =IF(E30<>"",E30*F2/100,"") | I30: =IF(E30<>"",E30+F30+G30+H30,"") | J30: =IF(E30<>"",H2,"") | K30: =IF(I30<>"",I30*J30,"") | N30: =IF(AND(K30<>"",L30<>""),(L30-K30)/L30,"") | O30: =IF(N30<>"",N30-J2/100-L2/100,"")
A31: =IF(B31<>"","Q-"&TEXT(ROW()-3,"000"),"") | F31: =IF(E31<>"",E31*B2/100,"") | G31: =IF(E31<>"",E31*D2/100,"") | H31: =IF(E31<>"",E31*F2/100,"") | I31: =IF(E31<>"",E31+F31+G31+H31,"") | J31: =IF(E31<>"",H2,"") | K31: =IF(I31<>"",I31*J31,"") | N31: =IF(AND(K31<>"",L31<>""),(L31-K31)/L31,"") | O31: =IF(N31<>"",N31-J2/100-L2/100,"")
A32: =IF(B32<>"","Q-"&TEXT(ROW()-3,"000"),"") | F32: =IF(E32<>"",E32*B2/100,"") | G32: =IF(E32<>"",E32*D2/100,"") | H32: =IF(E32<>"",E32*F2/100,"") | I32: =IF(E32<>"",E32+F32+G32+H32,"") | J32: =IF(E32<>"",H2,"") | K32: =IF(I32<>"",I32*J32,"") | N32: =IF(AND(K32<>"",L32<>""),(L32-K32)/L32,"") | O32: =IF(N32<>"",N32-J2/100-L2/100,"")
A33: =IF(B33<>"","Q-"&TEXT(ROW()-3,"000"),"") | F33: =IF(E33<>"",E33*B2/100,"") | G33: =IF(E33<>"",E33*D2/100,"") | H33: =IF(E33<>"",E33*F2/100,"") | I33: =IF(E33<>"",E33+F33+G33+H33,"") | J33: =IF(E33<>"",H2,"") | K33: =IF(I33<>"",I33*J33,"") | N33: =IF(AND(K33<>"",L33<>""),(L33-K33)/L33,"") | O33: =IF(N33<>"",N33-J2/100-L2/100,"")
A36: SUMMARY — Best Quote per SKU
A37: Best FOB (all quotes): | B37: =IFERROR(MIN(E4:E33),"No quotes yet")
A38: Best Gross Margin (all): | B38: =IFERROR(MAX(N4:N33),"No quotes yet")
A39: Worst FOB (all quotes): | B39: =IFERROR(MAX(E4:E33),"No quotes yet")

Sheet FOB_D2D_CALC
A1: LIONNA™ — FOB → Door-to-Door Cost Calculator · All SKUs
A2: Freight % | B2: Import Duty % | C2: QC & Misc % | D2: USD/BRL Rate | E2: Platform % | F2: Returns %
A3: 18 | B3: 20 | C3: 8 | D3: 5.2 | E3: 12 | F3: 8
A5: SKU | B5: Style Name | C5: Moment | D5: FOB (USD) Enter here | E5: Freight (=FOB×B3%) | F5: Duty (=FOB×C3%) | G5: QC (=FOB×D3%) | H5: Landed (USD) | I5: Landed (R$) | J5: Retail Min (R$) | K5: Gross Margin % | L5: Net Margin %
A6: 01 | B6: High-Waist Sculpt Legging | C6: Studio | E6: =IF(D6<>"",D6*$B$3/100,"") | F6: =IF(D6<>"",D6*$C$3/100,"") | G6: =IF(D6<>"",D6*$D$3/100,"") | H6: =IF(D6<>"",D6+E6+F6+G6,"") | I6: =IF(H6<>"",H6*$E$3,"") | J6: 209 | K6: =IF(AND(I6<>"",J6<>""),(J6-I6)/J6,"") | L6: =IF(K6<>"",K6-$F$3/100-$G$3/100,"")
A7: 02 | B7: Legging Soft Sculpt | C7: Studio | E7: =IF(D7<>"",D7*$B$3/100,"") | F7: =IF(D7<>"",D7*$C$3/100,"") | G7: =IF(D7<>"",D7*$D$3/100,"") | H7: =IF(D7<>"",D7+E7+F7+G7,"") | I7: =IF(H7<>"",H7*$E$3,"") | J7: 204 | K7: =IF(AND(I7<>"",J7<>""),(J7-I7)/J7,"") | L7: =IF(K7<>"",K7-$F$3/100-$G$3/100,"")
A8: 03 | B8: Sculpt Bra · Level 1 | C8: Studio | E8: =IF(D8<>"",D8*$B$3/100,"") | F8: =IF(D8<>"",D8*$C$3/100,"") | G8: =IF(D8<>"",D8*$D$3/100,"") | H8: =IF(D8<>"",D8+E8+F8+G8,"") | I8: =IF(H8<>"",H8*$E$3,"") | J8: 149 | K8: =IF(AND(I8<>"",J8<>""),(J8-I8)/J8,"") | L8: =IF(K8<>"",K8-$F$3/100-$G$3/100,"")
A9: 04 | B9: Support Top · Level 2 | C9: Studio | E9: =IF(D9<>"",D9*$B$3/100,"") | F9: =IF(D9<>"",D9*$C$3/100,"") | G9: =IF(D9<>"",D9*$D$3/100,"") | H9: =IF(D9<>"",D9+E9+F9+G9,"") | I9: =IF(H9<>"",H9*$E$3,"") | J9: 169 | K9: =IF(AND(I9<>"",J9<>""),(J9-I9)/J9,"") | L9: =IF(K9<>"",K9-$F$3/100-$G$3/100,"")
A10: 05 | B10: Urban Biker Short | C10: Morning Move | E10: =IF(D10<>"",D10*$B$3/100,"") | F10: =IF(D10<>"",D10*$C$3/100,"") | G10: =IF(D10<>"",D10*$D$3/100,"") | H10: =IF(D10<>"",D10+E10+F10+G10,"") | I10: =IF(H10<>"",H10*$E$3,"") | J10: 169 | K10: =IF(AND(I10<>"",J10<>""),(J10-I10)/J10,"") | L10: =IF(K10<>"",K10-$F$3/100-$G$3/100,"")
A11: 06 | B11: Premium Ribbed Tank | C11: Morning Move | E11: =IF(D11<>"",D11*$B$3/100,"") | F11: =IF(D11<>"",D11*$C$3/100,"") | G11: =IF(D11<>"",D11*$D$3/100,"") | H11: =IF(D11<>"",D11+E11+F11+G11,"") | I11: =IF(H11<>"",H11*$E$3,"") | J11: 129 | K11: =IF(AND(I11<>"",J11<>""),(J11-I11)/J11,"") | L11: =IF(K11<>"",K11-$F$3/100-$G$3/100,"")
A12: 07 | B12: Long Tank / Regata Soft | C12: Morning Move | E12: =IF(D12<>"",D12*$B$3/100,"") | F12: =IF(D12<>"",D12*$C$3/100,"") | G12: =IF(D12<>"",D12*$D$3/100,"") | H12: =IF(D12<>"",D12+E12+F12+G12,"") | I12: =IF(H12<>"",H12*$E$3,"") | J12: 139 | K12: =IF(AND(I12<>"",J12<>""),(J12-I12)/J12,"") | L12: =IF(K12<>"",K12-$F$3/100-$G$3/100,"")
A13: 08 | B13: Cropped Windbreaker / Clubhouse Layer | C13: Morning Move | E13: =IF(D13<>"",D13*$B$3/100,"") | F13: =IF(D13<>"",D13*$C$3/100,"") | G13: =IF(D13<>"",D13*$D$3/100,"") | H13: =IF(D13<>"",D13+E13+F13+G13,"") | I13: =IF(H13<>"",H13*$E$3,"") | J13: 289 | K13: =IF(AND(I13<>"",J13<>""),(J13-I13)/J13,"") | L13: =IF(K13<>"",K13-$F$3/100-$G$3/100,"")
A14: 09 | B14: Wide-Leg Active Pant | C14: The Work | E14: =IF(D14<>"",D14*$B$3/100,"") | F14: =IF(D14<>"",D14*$C$3/100,"") | G14: =IF(D14<>"",D14*$D$3/100,"") | H14: =IF(D14<>"",D14+E14+F14+G14,"") | I14: =IF(H14<>"",H14*$E$3,"") | J14: 244 | K14: =IF(AND(I14<>"",J14<>""),(J14-I14)/J14,"") | L14: =IF(K14<>"",K14-$F$3/100-$G$3/100,"")
A15: 10 | B15: Straight-Leg Active Pant | C15: The Work | E15: =IF(D15<>"",D15*$B$3/100,"") | F15: =IF(D15<>"",D15*$C$3/100,"") | G15: =IF(D15<>"",D15*$D$3/100,"") | H15: =IF(D15<>"",D15+E15+F15+G15,"") | I15: =IF(H15<>"",H15*$E$3,"") | J15: 229 | K15: =IF(AND(I15<>"",J15<>""),(J15-I15)/J15,"") | L15: =IF(K15<>"",K15-$F$3/100-$G$3/100,"")
A16: 11 | B16: Saia-Short Fluida | C16: Club & Court | E16: =IF(D16<>"",D16*$B$3/100,"") | F16: =IF(D16<>"",D16*$C$3/100,"") | G16: =IF(D16<>"",D16*$D$3/100,"") | H16: =IF(D16<>"",D16+E16+F16+G16,"") | I16: =IF(H16<>"",H16*$E$3,"") | J16: 194 | K16: =IF(AND(I16<>"",J16<>""),(J16-I16)/J16,"") | L16: =IF(K16<>"",K16-$F$3/100-$G$3/100,"")
A17: 12 | B17: Short Relaxed Urbano | C17: Club & Court | E17: =IF(D17<>"",D17*$B$3/100,"") | F17: =IF(D17<>"",D17*$C$3/100,"") | G17: =IF(D17<>"",D17*$D$3/100,"") | H17: =IF(D17<>"",D17+E17+F17+G17,"") | I17: =IF(H17<>"",H17*$E$3,"") | J17: 169 | K17: =IF(AND(I17<>"",J17<>""),(J17-I17)/J17,"") | L17: =IF(K17<>"",K17-$F$3/100-$G$3/100,"")
... A20: ACC | B20: Coverage Skirt (Accessory) | C20: After & Away | E20: =IF(D20<>"",D20*$B$3/100,"") | F20: =IF(D20<>"",D20*$C$3/100,"") | G20: =IF(D20<>"",D20*$D$3/100,"") | H20: =IF(D20<>"",D20+E20+F20+G20,"") | I20: =IF(H20<>"",H20*$E$3,"") | J20: 149 | K20: =IF(AND(I20<>"",J20<>""),(J20-I20)/J20,"") | L20: =IF(K20<>"",K20-$F$3/100-$G$3/100,"")

Sheet COLLECTION
A1: LIONNA™ — Phase 1 Capsule Collection · SS27 · 5 Moments
A2: SKU# | B2: Style Name | C2: Moment / Drop | D2: Tier | E2: Colors | F2: PCS/Color | G2: Total Units | H2: Retail Min (R$) | I2: Retail Max (R$) | J2: Fabric | K2: Assigned Supplier | L2: Status
A3: 01 | B3: High-Waist Sculpt Legging | C3: Studio | D3: A | E3: Onyx·Ivory·Stone·Charcoal | F3: 50 | G3: 200 | H3: 189 | I3: 239 | J3: 78% Nylon 22% Spandex · GSM 250–280 | K3: EnovStars | L3: Sourced
A4: 02 | B4: Legging Soft Sculpt | C4: Studio | D4: A | E4: Onyx·Stone·Ivory·Charcoal | F4: 50 | G4: 200 | H4: 179 | I4: 229 | J4: 78% Nylon 22% Spandex · GSM 220–250 | K4: EnovStars | L4: Sourced
A5: 03 | B5: Sculpt Bra · Level 1 | C5: Studio | D5: B | E5: Onyx·Ivory | F5: 100 | G5: 200 | H5: 129 | I5: 169 | J5: 78% Nylon 22% Spandex · GSM 180–220 | K5: Crossback Bra #5 | L5: Pending
A6: 04 | B6: Support Top · Level 2 | C6: Studio | D6: B | E6: Onyx·Stone | F6: 100 | G6: 200 | H6: 149 | I6: 189 | J6: 78% Nylon 22% Spandex · GSM 200–240 | K6: Crossback Bra #5 | L6: Pending
A7: 05 | B7: Urban Biker Short | C7: Morning Move | D7: A | E7: Onyx·Stone·Ivory·Charcoal | F7: 50 | G7: 200 | H7: 149 | I7: 189 | J7: 78% Nylon 22% Spandex · GSM 220–260 | K7: Anti-Exposure #15 | L7: Contacted
A8: 06 | B8: Premium Ribbed Tank | C8: Morning Move | D8: B | E8: Onyx·Ivory | F8: 100 | G8: 200 | H8: 109 | I8: 149 | J8: 90% Nylon 10% Spandex Ribbed | K8: EnovStars | L8: Sourced
A9: 07 | B9: Long Tank / Regata Soft | C9: Morning Move | D9: B | E9: Onyx·Stone | F9: 100 | G9: 200 | H9: 119 | I9: 159 | J9: 90% Nylon 10% Spandex Ribbed | K9: EnovStars | L9: Sourced
A10: 08 | B10: Cropped Windbreaker / Clubhouse Layer | C10: Morning Move | D10: B | E10: Stone·Ivory | F10: 100 | G10: 200 | H10: 249 | I10: 329 | J10: Nylon/Spandex · Stand collar · Zip | K10: Clubhouse #13 | L10: Pending
A11: 09 | B11: Wide-Leg Active Pant | C11: The Work | D11: C | E11: Onyx·Stone | F11: 50 | G11: 100 | H11: 219 | I11: 269 | J11: 95% Poly 5% Spandex Woven Tech | K11: AlOe #16 | L11: Sourced
A12: 10 | B12: Straight-Leg Active Pant | C12: The Work | D12: C | E12: Onyx·Charcoal | F12: 50 | G12: 100 | H12: 199 | I12: 259 | J12: Nylon/Spandex OR tech poly | K12: FITVOLT #17 | L12: Sourced
A13: 11 | B13: Saia-Short Fluida | C13: Club & Court | D13: C | E13: Ivory·Onyx | F13: 50 | G13: 100 | H13: 169 | I13: 219 | J13: Woven stretch OR nylon/spandex | K13: QUMOR #30 | L13: Pending
A14: 12 | B14: Short Relaxed Urbano | C14: Club & Court | D14: C | E14: Onyx·Stone | F14: 50 | G14: 100 | H14: 149 | I14: 189 | J14: 78% Nylon 22% Spandex OR light woven | K14: Anti-Exposure #15 | L14: Contacted
... A17: ACC | B17: Coverage Skirt (Accessory) | C17: After & Away | D17: ACC | E17: Onyx·Stone | F17: 50 | G17: 100 | H17: 129 | I17: 169 | J17: Fluid woven OR nylon GSM 120–150 | K17: EnovStars | L17: Sourced
A18: PHASE 1 TOTAL | G18: =SUM(G3:G17) | H18: Est. GMV R$450k–720k at sell-through

Sheet FABRICS
A1: LIONNA™ — Fabric Library · Approved Materials · Golden Rules
A2: Fabric Name | B2: Composition | C2: GSM Min | D2: GSM Max | E2: SKUs Assigned | F2: Mill/Supplier | G2: Oeko-Tex | H2: Recycled Pref. | I2: Notes
A3: Performance Nylon/Spandex | B3: 78% Polyamide · 22% Elastane | C3: 250 | D3: 280 | E3: 01,02,05,12,14 | F3: Mill TBD | G3: Yes | H3: Preferred | I3: Hero fabric. Naked Feel variant. Squat-proof required.
A4: Soft Sculpt Nylon | B4: 78% Polyamide · 22% Elastane | C4: 220 | D4: 250 | E4: 02 | F4: Mill TBD | G4: Yes | H4: Preferred | I4: Medium compression only. Wider front panel. Postpartum-friendly.
A5: Ribbed Performance Knit | B5: 90% Nylon · 10% Spandex | C5: 170 | D5: 190 | E5: 03,06,07 | F5: Mill TBD | G5: Yes | H5: Optional | I5: Refined rib texture. Must retain structure after 30 washes.
A6: Woven Stretch Tech | B6: 95% Polyester · 5% Spandex | C6: 140 | D6: 160 | E6: 09,11 | F6: Mill TBD | G6: No | H6: Optional | I6: Wide-leg pant and saia-short. Fluid drape essential.
A7: Scuba / Ponte Knit | B7: 70% Poly · 25% Nylon · 5% Spandex | C7: 280 | D7: 320 | E7: 13 | F7: Mill TBD | G7: No | H7: Optional | I7: Bomber jacket. Structured smooth surface. Holds shape.
A8: Fluid Cover Fabric | B8: 95% Poly · 5% Spandex woven | C8: 120 | D8: 140 | E8: ACC | F8: Mill TBD | G8: No | H8: Optional | I8: Coverage skirt. Fluid drape. Fully opaque.
A11: 10 GOLDEN RULES — Mandatory Quality Standards (Pass/Fail Gate)
A12: # | B12: Rule | C12: Specification | D12: Mandatory Test | E12: Evidence Required
A13: 01 | B13: Zero Transparency | C13: No visibility at 100% stretch, flash, or back-light | D13: Squat + flash photo + back-light on lightest colorway | E13: Photo evidence + written pass | F13: PASS / FAIL
A14: 02 | B14: No Body Marking | C14: No cellulite/underwear/sweat on medium tones | D14: On-body test · 3 body types · 30 min activity | E14: Photo before/after + measurement | F14: PASS / FAIL
A15: 03 | B15: Reinforced Seams | C15: Flatlock · 500-cycle stress test · no fraying | D15: Machine stress test · glute + inner thigh | E15: 500-cycle test certificate | F15: PASS / FAIL
A16: 04 | B16: Premium Fabric | C16: Nylon/spandex priority · Mill cert required | D16: Oeko-Tex 100 or REACH confirmation | E16: Mill certificate + lab report | F16: PASS / FAIL
A17: 05 | B17: Anatomical Waistband | C17: 8cm min · no rolling · grip strip inside | D17: 30-min movement test · must not shift or squeeze | E17: Video + photo before/after | F17: PASS / FAIL
A18: 06 | B18: Anti-Pilling | C18: ISO 12945-2 Grade 4 min after 2,000 cycles | D18: Lab pilling resistance test | E18: ISO 12945-2 lab certificate | F18: PASS / FAIL
A19: 07 | B19: Color Fastness | C19: ISO 105-C06 Grade 4–5 · no bleeding | D19: ISO 105-C06 + ISO 105-X12 lab tests | E19: Both ISO certificates | F19: PASS / FAIL
A20: 08 | B20: Shape Retention | C20: ASTM D2594 ≥95% after 50% stretch | D20: Lab stretch recovery test + 60 min wear | E20: ASTM D2594 certificate + photo | F20: PASS / FAIL
A21: 09 | B21: Bra Support | C21: Removable pad via pocket · never sewn in | D21: 50 jumping jacks · max 2cm displacement | E21: Video test + pad pocket photo | F21: PASS / FAIL
A22: 10 | B22: Sweat Management | C22: No marks >5cm after 45 min on medium tones | D22: 45-min cardio activity photo · panel measurement | E22: Photo evidence + measurements | F22: PASS / FAIL
